CommitMsgVerification/__init__.py
CommitMsgVerification/commit_m_ver.py
CommitMsgVerification-0.0.1.dist-info/METADATA
CommitMsgVerification-0.0.1.dist-info/WHEEL
CommitMsgVerification-0.0.1.dist-info/top_level.txt
CommitMsgVerification-0.0.1.dist-info/RECORD
