Metadata-Version: 2.1
Name: CommitMsgVerification
Version: 0.0.1
Summary: Returns the appropriate type of Git Commit Message.
Author: nastka)
Author-email: <anastasia.ganusina99@gmail.com>
Keywords: python,git,commit,message
Classifier: Development Status :: 1 - Planning
Classifier: Intended Audience :: Developers
Classifier: Programming Language :: Python :: 3
Classifier: Operating System :: Unix
Classifier: Operating System :: MacOS :: MacOS X
Classifier: Operating System :: Microsoft :: Windows
Requires-Dist: GitPython
Requires-Dist: importlib
Requires-Dist: sys
Requires-Dist: inspect
Requires-Dist: os
Requires-Dist: pathlib
Requires-Dist: contextlib
